octopus32/__init__.py
octopus32/utils.py
octopus32-0.1.1.dist-info/METADATA
octopus32-0.1.1.dist-info/WHEEL
octopus32-0.1.1.dist-info/top_level.txt
octopus32-0.1.1.dist-info/RECORD
